mcp_server_esignatures/__init__.py
mcp_server_esignatures/input_schema_contracts.py
mcp_server_esignatures/input_schema_document_elements.py
mcp_server_esignatures/input_schema_template_collaborators.py
mcp_server_esignatures/input_schema_templates.py
mcp_server_esignatures/server.py
mseep_mcp_server_esignatures-0.1.4.dist-info/licenses/LICENSE
mseep_mcp_server_esignatures-0.1.4.dist-info/METADATA
mseep_mcp_server_esignatures-0.1.4.dist-info/WHEEL
mseep_mcp_server_esignatures-0.1.4.dist-info/entry_points.txt
mseep_mcp_server_esignatures-0.1.4.dist-info/top_level.txt
mseep_mcp_server_esignatures-0.1.4.dist-info/RECORD
